ez_app/__init__.py
ez_app/config.py
ez_app/future_fields.py
ez_app/resources.py
ez_app/test.py
ez_app-1.0.3.dist-info/METADATA
ez_app-1.0.3.dist-info/WHEEL
ez_app-1.0.3.dist-info/top_level.txt
ez_app-1.0.3.dist-info/RECORD
