Metadata-Version: 2.1
Name: ez-app
Version: 1.0.3
Summary: app toolkits
Author: TunaFish2K
Author-email: tunafish2k@163.com
Keywords: app
Requires-Python: >=3
